pytip/__init__.py
pytip/calender/__init__.py
pytip/calender/base.py
pytip/calender/datago.py
pytip/calender/koscom.py
pytip/json/browsers.json
pytip/tools/__init__.py
pytip/tools/base.py
pytip/tools/item.py
pytip/tools/plot.py
pytip/tools/sheet.py
pytip/tools/table.py
pytip/tools/tokens.py
pytip/utils/__init__.py
pytip/utils/base.py
pytip/utils/celery.py
pytip/utils/checker.py
pytip/utils/deco.py
pytip/utils/file.py
pytip/utils/func.py
pytip/utils/web.py
pytip-0.1.10.dist-info/METADATA
pytip-0.1.10.dist-info/WHEEL
pytip-0.1.10.dist-info/top_level.txt
pytip-0.1.10.dist-info/RECORD
