Metadata-Version: 2.1
Name: pytip
Version: 0.1.10
Home-page: https://github.com/YongBeomKim/pytip
Author: momukji lab
Author-email: ybkim@momukji.com
License: MIT
Keywords: pytip
Classifier: Programming Language :: Python :: 3.9
Classifier: Programming Language :: Python :: 3.10
Classifier: Programming Language :: Python :: 3.11
Requires-Python: >=3
Requires-Dist: xlrd
Requires-Dist: termcolor
Requires-Dist: openpyxl
Requires-Dist: pandas
Requires-Dist: numpy
Requires-Dist: tqdm
